ShujuKeshihuaDeJichuzhishiFix1/README.md
ShujuKeshihuaDeJichuzhishiFix1/__init__.py
ShujuKeshihuaDeJichuzhishiFix1/__main__.py
ShujuKeshihuaDeJichuzhishiFix1/file.epub
ShujuKeshihuaDeJichuzhishiFix1/index.html
ShujuKeshihuaDeJichuzhishiFix1/css/__init__.py
ShujuKeshihuaDeJichuzhishiFix1/css/annotations.css
ShujuKeshihuaDeJichuzhishiFix1/css/main.css
ShujuKeshihuaDeJichuzhishiFix1/css/normalize.css
ShujuKeshihuaDeJichuzhishiFix1/css/popup.css
ShujuKeshihuaDeJichuzhishiFix1/font/__init__.py
ShujuKeshihuaDeJichuzhishiFix1/font/fontello.eot
ShujuKeshihuaDeJichuzhishiFix1/font/fontello.svg
ShujuKeshihuaDeJichuzhishiFix1/font/fontello.ttf
ShujuKeshihuaDeJichuzhishiFix1/font/fontello.woff
ShujuKeshihuaDeJichuzhishiFix1/img/__init__.py
ShujuKeshihuaDeJichuzhishiFix1/img/annotator-glyph-sprite.png
ShujuKeshihuaDeJichuzhishiFix1/img/annotator-icon-sprite.png
ShujuKeshihuaDeJichuzhishiFix1/img/apple-touch-icon.png
ShujuKeshihuaDeJichuzhishiFix1/img/cancelfullscreen.png
ShujuKeshihuaDeJichuzhishiFix1/img/close.png
ShujuKeshihuaDeJichuzhishiFix1/img/fullscreen.png
ShujuKeshihuaDeJichuzhishiFix1/img/loader.gif
ShujuKeshihuaDeJichuzhishiFix1/img/menu-icon.png
ShujuKeshihuaDeJichuzhishiFix1/img/save.png
ShujuKeshihuaDeJichuzhishiFix1/img/saved.png
ShujuKeshihuaDeJichuzhishiFix1/img/settings-s.png
ShujuKeshihuaDeJichuzhishiFix1/img/settings.png
ShujuKeshihuaDeJichuzhishiFix1/img/star.png
ShujuKeshihuaDeJichuzhishiFix1/js/__init__.py
ShujuKeshihuaDeJichuzhishiFix1/js/epub.js
ShujuKeshihuaDeJichuzhishiFix1/js/epub.min.js
ShujuKeshihuaDeJichuzhishiFix1/js/epub.min.map
ShujuKeshihuaDeJichuzhishiFix1/js/hooks.min.js
ShujuKeshihuaDeJichuzhishiFix1/js/hooks.min.map
ShujuKeshihuaDeJichuzhishiFix1/js/reader.js
ShujuKeshihuaDeJichuzhishiFix1/js/reader.js.map
ShujuKeshihuaDeJichuzhishiFix1/js/reader.min.js
ShujuKeshihuaDeJichuzhishiFix1/js/reader.min.map
ShujuKeshihuaDeJichuzhishiFix1/js/hooks/__init__.py
ShujuKeshihuaDeJichuzhishiFix1/js/hooks/extensions/__init__.py
shuju_keshihua_de_jichuzhishi_fix1-2025.3.24.0.dist-info/METADATA
shuju_keshihua_de_jichuzhishi_fix1-2025.3.24.0.dist-info/WHEEL
shuju_keshihua_de_jichuzhishi_fix1-2025.3.24.0.dist-info/entry_points.txt
shuju_keshihua_de_jichuzhishi_fix1-2025.3.24.0.dist-info/top_level.txt
shuju_keshihua_de_jichuzhishi_fix1-2025.3.24.0.dist-info/RECORD
